drogher/__init__.py
drogher/__init__.pyc
drogher/package/__init__.py
drogher/package/__init__.pyc
drogher/package/base.py
drogher/package/base.pyc
drogher/package/dhl.py
drogher/package/dhl.pyc
drogher/package/fedex.py
drogher/package/fedex.pyc
drogher/package/ontrac.py
drogher/package/ontrac.pyc
drogher/package/ups.py
drogher/package/ups.pyc
drogher/package/usps.py
drogher/package/usps.pyc
drogher-0.0.2.dist-info/DESCRIPTION.rst
drogher-0.0.2.dist-info/METADATA
drogher-0.0.2.dist-info/RECORD
drogher-0.0.2.dist-info/WHEEL
drogher-0.0.2.dist-info/metadata.json
drogher-0.0.2.dist-info/top_level.txt
tests/__init__.py
tests/__init__.pyc
tests/test_drogher.py
tests/test_package.py
tests/__pycache__/test_drogher.cpython-27-PYTEST.pyc
tests/__pycache__/test_package.cpython-27-PYTEST.pyc
