Metadata-Version: 2.0
Name: drogher
Version: 0.0.2
Summary: Identify shippers and valid tracking numbers from package barcodes
Home-page: https://github.com/jbittel/drogher
Author: Jason Bittel
Author-email: jason.bittel@gmail.com
License: BSD
Platform: UNKNOWN
Classifier: Development Status :: 3 - Alpha
Classifier: Intended Audience :: Developers
Classifier: License :: OSI Approved :: BSD License
Classifier: Operating System :: OS Independent
Classifier: Programming Language :: Python
Classifier: Programming Language :: Python :: 2
Classifier: Programming Language :: Python :: 2.7
Classifier: Programming Language :: Python :: 3
Classifier: Programming Language :: Python :: 3.5
Classifier: Topic :: Software Development :: Libraries :: Python Modules
Classifier: Topic :: Utilities
